csapptools/__init__.py
csapptools/librariesiolib.py
csapptools/pypilib.py
csapptools-1.0.0.dist-info/LICENSE.txt
csapptools-1.0.0.dist-info/METADATA
csapptools-1.0.0.dist-info/WHEEL
csapptools-1.0.0.dist-info/top_level.txt
csapptools-1.0.0.dist-info/RECORD
