Metadata-Version: 2.1
Name: csapptools
Version: 1.0.0
Summary: Scraping tools for https://github.com/adamcysec/CSAPP
Home-page: https://github.com/adamcysec/csapptools
Author: adamcysec
Project-URL: repository, https://github.com/adamcysec/csapptools
Classifier: Programming Language :: Python :: 3
Classifier: License :: OSI Approved :: MIT License
Classifier: Operating System :: Microsoft :: Windows
Classifier: Operating System :: MacOS :: MacOS X
Classifier: Operating System :: Unix
Requires-Python: >=3.6
License-File: LICENSE.txt
